setup.py
vis1108/Binomialdistribution.py
vis1108/Gaussiandistribution.py
vis1108/Generaldistribution.py
vis1108/__init__.py
vis1108.egg-info/PKG-INFO
vis1108.egg-info/SOURCES.txt
vis1108.egg-info/dependency_links.txt
vis1108.egg-info/not-zip-safe
vis1108.egg-info/top_level.txt