Metadata-Version: 1.0
Name: vis1108
Version: 0.3
Summary: Gaussian and binomial distributions
Home-page: UNKNOWN
Author: Vishnusai
Author-email: myemail@something.com
License: UNKNOWN
Platform: UNKNOWN
